tensorlake/__init__.py
tensorlake/applications/__init__.py
tensorlake/applications/algorithms/validate_user_object.py
tensorlake/applications/applications.py
tensorlake/applications/blob_store/__init__.py
tensorlake/applications/blob_store/blob.py
tensorlake/applications/blob_store/blob_store.py
tensorlake/applications/blob_store/local_fs_blob_store.py
tensorlake/applications/blob_store/s3_blob_store.py
tensorlake/applications/cloud_events.py
tensorlake/applications/function/application_call.py
tensorlake/applications/function/function_call.py
tensorlake/applications/function/introspect.py
tensorlake/applications/function/type_hints.py
tensorlake/applications/function/user_data_serializer.py
tensorlake/applications/image.py
tensorlake/applications/interface/README.md
tensorlake/applications/interface/__init__.py
tensorlake/applications/interface/_pretty_print.py
tensorlake/applications/interface/awaitables.py
tensorlake/applications/interface/decorators.py
tensorlake/applications/interface/exceptions.py
tensorlake/applications/interface/file.py
tensorlake/applications/interface/function.py
tensorlake/applications/interface/image.py
tensorlake/applications/interface/request.py
tensorlake/applications/interface/request_context.py
tensorlake/applications/interface/retries.py
tensorlake/applications/interface/run.py
tensorlake/applications/internal_logger.py
tensorlake/applications/local/class_instance_store.py
tensorlake/applications/local/future.py
tensorlake/applications/local/future_run/function_call_future_run.py
tensorlake/applications/local/future_run/future_run.py
tensorlake/applications/local/future_run/list_future_run.py
tensorlake/applications/local/future_run/return_output_future_run.py
tensorlake/applications/local/request.py
tensorlake/applications/local/request_context/handlers/add_metrics.py
tensorlake/applications/local/request_context/handlers/progress_update.py
tensorlake/applications/local/request_context/handlers/request_state/commit_write.py
tensorlake/vendor/nanoid/nanoid-2.0.0.dist-info/INSTALLER
tensorlake/vendor/nanoid/nanoid-2.0.0.dist-info/LICENSE
tensorlake/vendor/nanoid/nanoid-2.0.0.dist-info/METADATA
tensorlake/vendor/nanoid/nanoid-2.0.0.dist-info/RECORD
tensorlake/vendor/nanoid/nanoid-2.0.0.dist-info/REQUESTED
tensorlake/vendor/nanoid/nanoid-2.0.0.dist-info/WHEEL
tensorlake/vendor/nanoid/nanoid-2.0.0.dist-info/top_level.txt
tensorlake/vendor/structlog/structlog-25.5.0.dist-info/METADATA
tensorlake/vendor/structlog/structlog-25.5.0.dist-info/RECORD
tensorlake/vendor/structlog/structlog-25.5.0.dist-info/WHEEL
tensorlake/vendor/structlog/structlog-25.5.0.dist-info/licenses/LICENSE-APACHE
tensorlake/vendor/structlog/structlog-25.5.0.dist-info/licenses/LICENSE-MIT
tensorlake/vendor/structlog/structlog-25.5.0.dist-info/licenses/NOTICE
tensorlake-0.3.2.dist-info/LICENSE
tensorlake-0.3.2.dist-info/METADATA
tensorlake-0.3.2.dist-info/WHEEL
tensorlake-0.3.2.dist-info/entry_points.txt
tensorlake-0.3.2.dist-info/RECORD
