Metadata-Version: 2.3
Name: tensorlake
Version: 0.3.2
Summary: Tensorlake SDK for Document Ingestion API and Serverless Applications
Home-page: https://github.com/tensorlakeai/tensorlake
Author: Tensorlake Inc.
Author-email: support@tensorlake.ai
Requires-Python: >=3.10,<4.0
Classifier: Programming Language :: Python :: 3
Classifier: Programming Language :: Python :: 3.10
Classifier: Programming Language :: Python :: 3.11
Classifier: Programming Language :: Python :: 3.12
Classifier: Programming Language :: Python :: 3.13
Requires-Dist: click (==8.3.1)
Requires-Dist: grpcio (==1.76.0)
Requires-Dist: grpcio-tools (==1.76.0)
Requires-Dist: httpx-sse (>=0.4.1,<0.5.0)
Requires-Dist: httpx[http2] (>=0.27.2,<1.0)
Requires-Dist: pydantic (>=2.0,<3.0)
Requires-Dist: python-magic (>=0.4.27,<0.5.0)
Requires-Dist: pyyaml (>=6.0.3,<7.0.0)
Requires-Dist: rich (==14.2.0)
Requires-Dist: tomlkit (>=0.13.3,<0.14.0)
Project-URL: Repository, https://github.com/tensorlakeai/tensorlake
